koxs_file_editor/__init__.py
koxs_file_editor/batch_operations.py
koxs_file_editor/core.py
koxs_file_editor/file_operations.py
koxs_file_editor/large_file_operations.py
koxs_file_editor/line_operations.py
koxs_file_editor/query_operations.py
koxs_file_editor/regex_operations.py
koxs_file_editor/text_operations.py
koxs_file_editor/undo_redo.py
koxs_file_editor/utils.py
koxs_file_editor-0.1.0.dist-info/licenses/LICENSE
koxs_file_editor-0.1.0.dist-info/METADATA
koxs_file_editor-0.1.0.dist-info/WHEEL
koxs_file_editor-0.1.0.dist-info/top_level.txt
koxs_file_editor-0.1.0.dist-info/RECORD
