Metadata-Version: 2.4
Name: koxs-file-editor
Version: 0.1.0
Summary: 一个功能强大的纯Python文件编辑器，支持批量操作、撤销重做、大文件处理和正则表达式
Home-page: https://github.com/yourusername/koxs-file-editor
Author: koxs
Author-email: koxs@example.com
Project-URL: Documentation, https://github.com/yourusername/koxs-file-editor/wiki
Project-URL: Source, https://github.com/yourusername/koxs-file-editor
Project-URL: Tracker, https://github.com/yourusername/koxs-file-editor/issues
Keywords: file editor,text processing,batch operations,undo redo,regex,large files
Classifier: Development Status :: 4 - Beta
Classifier: Intended Audience :: Developers
Classifier: License :: OSI Approved :: MIT License
Classifier: Programming Language :: Python :: 3
Classifier: Programming Language :: Python :: 3.7
Classifier: Programming Language :: Python :: 3.8
Classifier: Programming Language :: Python :: 3.9
Classifier: Programming Language :: Python :: 3.10
Classifier: Programming Language :: Python :: 3.11
Classifier: Operating System :: OS Independent
Classifier: Topic :: Text Editors
Classifier: Topic :: Text Processing
Classifier: Topic :: Utilities
Requires-Python: >=3.7
License-File: LICENSE
Dynamic: author
Dynamic: author-email
Dynamic: classifier
Dynamic: description
Dynamic: description-content-type
Dynamic: home-page
Dynamic: keywords
Dynamic: license-file
Dynamic: project-url
Dynamic: requires-python
Dynamic: summary
